{
  "ssltype": "https://",
  "host": "www.concrete-jungle.org",
  "uBase": "/FoodParent2.0",
  "uBaseForRouter": "/FoodParent2.0/",
  "bTestMail": true,



  "uServer": "/server/",
  "uDist": "/dist/",
  "uSetting": "/dist/setting/",
  "uStaticImage": "/static/images/",
  "uContentImage": "/content/images/",
  "uRelativeImageUpload": "./../content/images/",

  "sServerDateFormat": "YYYY-MM-DD HH:mm:ss",
  "sEXIFDateFormat": "YYYY-MM-DD HH-mm-ss",
  "sUIDateFormat": "MM/DD/YY",

  "iGallerySlideInterval": 7500,

  "fKGToG": 1000,
  "fLBSTOG": 453.592,
  "fGToLBS": 0.00220462,
  "iAmountPrecision": 2,

  "iDeadFlagId": 1,

  "sNoteImagePrefix": "note_",
  "sDonateImagePrefix": "donate_"

}
